svgwrite/__init__.py
svgwrite/animate.py
svgwrite/base.py
svgwrite/container.py
svgwrite/drawing.py
svgwrite/elementfactory.py
svgwrite/etree.py
svgwrite/filters.py
svgwrite/gradients.py
svgwrite/image.py
svgwrite/masking.py
svgwrite/mixins.py
svgwrite/params.py
svgwrite/path.py
svgwrite/pattern.py
svgwrite/shapes.py
svgwrite/solidcolor.py
svgwrite/text.py
svgwrite/utils.py
svgwrite/validator2.py
svgwrite/version.py
svgwrite/data/__init__.py
svgwrite/data/colors.py
svgwrite/data/full11.py
svgwrite/data/pattern.py
svgwrite/data/svgparser.py
svgwrite/data/tiny12.py
svgwrite/data/typechecker.py
svgwrite/data/types.py
svgwrite/extensions/__init__.py
svgwrite/extensions/inkscape.py
svgwrite/extensions/shapes.py
svgwrite-1.4.2.dist-info/LICENSE.TXT
svgwrite-1.4.2.dist-info/METADATA
svgwrite-1.4.2.dist-info/WHEEL
svgwrite-1.4.2.dist-info/top_level.txt
svgwrite-1.4.2.dist-info/RECORD
