Metadata-Version: 2.1
Name: svgwrite
Version: 1.4.2
Summary: A Python library to create SVG drawings.
Home-page: http://github.com/mozman/svgwrite.git
Download-URL: http://github.com/mozman/svgwrite/releases
Author: Manfred Moitzi
Author-email: me@mozman.at
License: MIT License
Platform: OS Independent
Classifier: Development Status :: 7 - Inactive
Classifier: License :: OSI Approved :: MIT License
Classifier: Operating System :: OS Independent
Classifier: Programming Language :: Python :: 3
Classifier: Programming Language :: Python :: 3.6
Classifier: Programming Language :: Python :: 3.7
Classifier: Programming Language :: Python :: 3.8
Classifier: Programming Language :: Python :: 3.9
Classifier: Programming Language :: Python :: 3.10
Classifier: Programming Language :: Python :: Implementation :: CPython
Classifier: Programming Language :: Python :: Implementation :: PyPy
Classifier: Intended Audience :: Developers
Classifier: Topic :: Multimedia :: Graphics
Classifier: Topic :: Software Development :: Libraries :: Python Modules
Provides: svgwrite
Requires-Python: >=3.6
License-File: LICENSE.TXT
